ascii2graph/__init__.py
ascii2graph/errors.py
ascii2graph/graph.py
ascii2graph-0.3.3.dist-info/LICENSE
ascii2graph-0.3.3.dist-info/WHEEL
ascii2graph-0.3.3.dist-info/METADATA
ascii2graph-0.3.3.dist-info/RECORD
